defcon_utils/__init__.py
defcon_utils/base_api.py
defcon_utils/cloud_storage.py
defcon_utils/common.py
defcon_utils/date_time_helper.py
defcon_utils/exceptions.py
defcon_utils/mail.py
defcon_utils/parser.py
defcon_utils/url_shortner.py
defcon_utils-0.0.4.dist-info/METADATA
defcon_utils-0.0.4.dist-info/WHEEL
defcon_utils-0.0.4.dist-info/top_level.txt
defcon_utils-0.0.4.dist-info/RECORD
