Metadata-Version: 2.1
Name: defcon-utils
Version: 0.0.4
Summary: Common utility functions and classes by DefCon-007
Home-page: UNKNOWN
Author: Ayush Goyal
Author-email: ayushgoyal.iitkgp@gmail.com
License: UNKNOWN
Keywords: python
Platform: UNKNOWN
Classifier: Development Status :: 3 - Alpha
Classifier: Intended Audience :: Education
Classifier: Programming Language :: Python :: 2
Classifier: Programming Language :: Python :: 3
Classifier: Operating System :: MacOS :: MacOS X
Classifier: Operating System :: Microsoft :: Windows
Requires-Dist: requests
Requires-Dist: python-dateutil
Requires-Dist: pytz
Requires-Dist: boto3 (==1.13.4)
Requires-Dist: sendgrid (==6.3.1)
